{
    "apps": [
        {
            "app": {
                "id": 18,
                "uuid": "125338ea-c1b7-492b-9aa1-2e55432f7c13",
                "name": "Theme Me",
                "author": "Mike Boynton",
                "author_id": 392012772189274112,
                "author_link": "",
                "desc": "Allows you to select a random Droptop theme and you can save up to eight custom themes and hot load them.\nNo need to install a custom theme again once it is saved.\n\nFeatures\n\n    Toggle Theme Previews\n    Random theme every 24hrs, 1hr or 1 minute.\n    Toggle random theme feature on/off\n    Shows you the theme you are currently using.\n",
                "version": "1.02",
                "official_link": "",
                "direct_download_link": "https://github.com/Droptop-Four/Droptop-Community-Apps/raw/main/Apps/Theme%20Me%20-%20Mike%20Boynton%20(Droptop%20App).rmskin",
                "secondary_link": "",
                "image_url": "https://raw.githubusercontent.com/Droptop-Four/GlobalData/main/data/community_apps/img/Theme_Me-Mike_Boynton.webp",
                "authorised_members": [584542239900827665, 330345930198876161, 392012772189274112]
            }
        },
        {
            "app": {
                "id": 16,
                "uuid": "27aeb9cd-be20-400d-857c-4b199aeadae1",
                "name": "Feeder",
                "author": "Cariboudjan",
                "author_id": 584542239900827665,
                "author_link": "https://github.com/Cariboudjan",
                "desc": "RSS Feeder for Lifehacker, Yahoo! News, Wall Street Journal, CBC News, The New Yorker, New York Times, and The Lincoln Project.",
                "version": "0.5",
                "official_link": "",
                "direct_download_link": "https://github.com/Droptop-Four/Droptop-Community-Apps/raw/main/Apps/Feeder%20-%20Cariboudjan%20(Droptop%20App).rmskin",
                "secondary_link": "",
                "image_url": "https://raw.githubusercontent.com/Droptop-Four/GlobalData/main/data/community_apps/img/Feeder-Cariboudjan.webp",
                "authorised_members": [584542239900827665, 330345930198876161, 584542239900827665]
            }
        },
        {
            "app": {
                "id": 14,
                "uuid": "c6bfeed4-6179-41cd-9ac9-322652111cf9",
                "name": "Game Hub",
                "author": "Phan",
                "author_id": 561681705782607882,
                "author_link": "",
                "desc": "This is a community app to keep your favorite games organized.",
                "version": "0.5",
                "official_link": "",
                "direct_download_link": "https://github.com/Droptop-Four/Droptop-Community-Apps/raw/main/Apps/Game%20Hub%20-%20Phan%20(Droptop%20App).rmskin",
                "secondary_link": "",
                "image_url": "https://raw.githubusercontent.com/Droptop-Four/GlobalData/main/data/community_apps/img/Game_Hub-Phan.webp",
                "authorised_members": [584542239900827665, 330345930198876161, 561681705782607882]
            }
        },
        {
            "app": {
                "id": 13,
                "uuid": "b9451f72-c9cc-4d36-b012-99031e842b1d",
                "name": "Shortcut",
                "author": "Phan",
                "author_id": 561681705782607882,
                "author_link": "",
                "desc": "This is a community app that allwos you to add a shortcut of any program or file in your Droptop bar.",
                "version": "0.6",
                "official_link": "",
                "direct_download_link": "https://github.com/Droptop-Four/Droptop-Community-Apps/raw/main/Apps/Shortcut%20-%20Phan%20(Droptop%20App).rmskin",
                "secondary_link": "",
                "image_url": "https://raw.githubusercontent.com/Droptop-Four/GlobalData/main/data/community_apps/img/Shortcut-Phan.webp",
                "authorised_members": [584542239900827665, 330345930198876161, 561681705782607882]
            }
        },
        {
            "app": {
                "id": 12,
                "uuid": "216f917f-0f37-42f5-b218-06feddc574da",
                "name": "SearchBar",
                "author": "Mike Boynton",
                "author_id": 392012772189274112,
                "author_link": "",
                "desc": "Search from a variety of search engines & stores in just a few clicks",
                "version": "2.1",
                "official_link": "",
                "direct_download_link": "https://github.com/Droptop-Four/Droptop-Community-Apps/raw/main/Apps/SearchBar%20-%20Mike%20Boynton%20(Droptop%20App).rmskin",
                "secondary_link": "",
                "image_url": "https://raw.githubusercontent.com/Droptop-Four/GlobalData/main/data/community_apps/img/SearchBar-Mike_Boynton.webp",
                "authorised_members": [584542239900827665, 330345930198876161, 392012772189274112]
            }
        },
        {
            "app": {
                "id": 11,
                "uuid": "77b82067-a549-47f9-89ae-756165ae3bd0",
                "name": "Gradient Bar",
                "author": "Phan",
                "author_id": 561681705782607882,
                "author_link": "",
                "desc": "This is a community app that allows you to customize the colors of the top bar.",
                "version": "0.7",
                "official_link": "",
                "direct_download_link": "https://github.com/Droptop-Four/Droptop-Community-Apps/raw/main/Apps/Gradient%20Bar%20-%20Phan%20(Droptop%20App).rmskin",
                "secondary_link": "",
                "image_url": "https://raw.githubusercontent.com/Droptop-Four/GlobalData/main/data/community_apps/img/Gradient_Bar-Phan.webp",
                "authorised_members": [584542239900827665, 330345930198876161, 561681705782607882]
            }
        },
        {
            "app": {
                "id": 10,
                "uuid": "671e8670-e582-4269-9820-3dcf508abf4d",
                "name": "Color Mode Toggle",
                "author": "Cariboudjan",
                "author_id": 584542239900827665,
                "author_link": "https://github.com/Cariboudjan",
                "desc": "On compatible themes, one-click toggle switching between dark mode and light mode.",
                "version": "1.0",
                "official_link": "",
                "direct_download_link": "https://github.com/Droptop-Four/Droptop-Community-Apps/raw/main/Apps/Color%20Mode%20Toggle%20-%20Cariboudjan%20(Droptop%20App).rmskin",
                "secondary_link": "",
                "image_url": "https://raw.githubusercontent.com/Droptop-Four/GlobalData/main/data/community_apps/img/Color_Mode_Toggle-Cariboudjan.webp",
                "authorised_members": [584542239900827665, 330345930198876161, 584542239900827665]
            }
        },
        {
            "app": {
                "id": 9,
                "uuid": "b070cf99-c013-4744-932d-cb4e9102ae2a",
                "name": "Media Control",
                "author": "Yaron",
                "author_id": 709053559836246137,
                "author_link": "https://github.com/Yaron2334",
                "desc": "Alternative WebNowPlaying media control center.Requires the WebNowPlaying extension for Chrome, Brave, Firefox, or Edge browsers.",
                "version": "1.1.1",
                "official_link": "https://github.com/Yaron2334/Media-Control",
                "direct_download_link": "https://github.com/Droptop-Four/Droptop-Community-Apps/raw/main/Apps/Media%20Control%20-%20Yaron%20(Droptop%20App).rmskin",
                "secondary_link": "",
                "image_url": "https://raw.githubusercontent.com/Droptop-Four/GlobalData/main/data/community_apps/img/Media_Control-Yaron.webp",
                "authorised_members": [584542239900827665, 330345930198876161, 709053559836246137]
            }
        },
        {
            "app": {
                "id": 8,
                "uuid": "bded0a8f-4df2-4b85-aac5-a4a97ce2e8db",
                "name": "JaxCore",
                "author": "Jax",
                "author_id": 341522422836625408,
                "author_link": "https://github.com/EnhancedJax",
                "desc": "Allows integration of Vallistart 3.0 with the Droptop home button, as well as shortcuts to YourMixer, QuickNotes, and Keylauncher from JaxCore.\n- JaxCore and related modules required\n- Module download links included inside app.",
                "version": "1.0",
                "official_link": "",
                "direct_download_link": "https://github.com/Droptop-Four/Droptop-Community-Apps/raw/main/Apps/JaxCore%20-%20JaxCore%20(Droptop%20App).rmskin",
                "secondary_link": "",
                "image_url": "https://raw.githubusercontent.com/Droptop-Four/GlobalData/main/data/community_apps/img/JaxCore-Jax.webp",
                "authorised_members": [584542239900827665, 330345930198876161, 341522422836625408]
            }
        },
        {
            "app": {
                "id": 7,
                "uuid": "e4e90147-d711-46a7-93c7-2455b7975691",
                "name": "System Monitor",
                "author": "Yaron",
                "author_id": 709053559836246137,
                "author_link": "https://github.com/Yaron2334",
                "desc": "Displays CPU, GPU, RAM, Voltage, and other system resources within the app and on the top bar.",
                "version": "1.6.0818",
                "official_link": "https://github.com/Yaron2334/SystemMonitor",
                "direct_download_link": "https://github.com/Droptop-Four/Droptop-Community-Apps/raw/main/Apps/System%20Monitor%20-%20Yaron%20(Droptop%20App).rmskin",
                "secondary_link": "",
                "image_url": "https://raw.githubusercontent.com/Droptop-Four/GlobalData/main/data/community_apps/img/System_Monitor-Yaron.webp",
                "authorised_members": [584542239900827665, 330345930198876161, 709053559836246137]
            }
        },
        {
            "app": {
                "id": 6,
                "uuid": "55b4b06d-85bd-424c-8150-4fbf0daf8cd5",
                "name": "Quick Settings",
                "author": "Cariboudjan",
                "author_id": 584542239900827665,
                "author_link": "https://github.com/Cariboudjan",
                "desc": "Toggles the Quick Settings menu (Win+A) in Windows 11, or the Action Center in Windows 10.",
                "version": "1.0",
                "official_link": "",
                "direct_download_link": "https://github.com/Droptop-Four/Droptop-Community-Apps/raw/main/Apps/Quick%20Settings%20-%20Cariboudjan%20(Droptop%20App).rmskin",
                "secondary_link": "",
                "image_url": "https://raw.githubusercontent.com/Droptop-Four/GlobalData/main/data/community_apps/img/Quick_Settings-Cariboudjan.webp",
                "authorised_members": [584542239900827665, 330345930198876161, 584542239900827665]
            }
        },
        {
            "app": {
                "id": 5,
                "uuid": "f98385fd-2a99-4cde-a0b4-5aaa84289497",
                "name": "Disks",
                "author": "Phan",
                "author_id": 561681705782607882,
                "author_link": "",
                "desc": "Shortcuts of up to 5 disk drives and displays remaining gigabytes.",
                "version": "1.5",
                "official_link": "",
                "direct_download_link": "https://github.com/Droptop-Four/Droptop-Community-Apps/raw/main/Apps/Disks%20-%20Phan%20(Droptop%20App).rmskin",
                "secondary_link": "",
                "image_url": "https://raw.githubusercontent.com/Droptop-Four/GlobalData/main/data/community_apps/img/Disks-Phan.webp",
                "authorised_members": [584542239900827665, 330345930198876161, 561681705782607882]
            }
        },
        {
            "app": {
                "id": 4,
                "uuid": "73e48dae-9039-44d7-aedc-f8cbe8405c2f",
                "name": "Recycle Bin",
                "author": "Phan",
                "author_id": 561681705782607882,
                "author_link": "",
                "desc": "Displays the recycle bin. The bin icon will change depending on how much is in the recycle bin. Drag & drop to the icon to delete files.",
                "version": "1.1",
                "official_link": "",
                "direct_download_link": "https://github.com/Droptop-Four/Droptop-Community-Apps/raw/main/Apps/Recycle%20Bin%20-%20Phan%20(Droptop%20App).rmskin",
                "secondary_link": "",
                "image_url": "https://raw.githubusercontent.com/Droptop-Four/GlobalData/main/data/community_apps/img/Recycle_Bin-Phan.webp",
                "authorised_members": [584542239900827665, 330345930198876161, 561681705782607882]
            }
        },
        {
            "app": {
                "id": 3,
                "uuid": "0a4e9e6d-8e0c-4c7a-bdbd-a9a1adf8e711",
                "name": "Location",
                "author": "notAperson",
                "author_id": 736395826670207088,
                "author_link": "",
                "desc": "Shows your IP and location information.",
                "version": "1.8",
                "official_link": "https://github.com/notAperson535/Location-For-Droptop",
                "direct_download_link": "https://github.com/Droptop-Four/Droptop-Community-Apps/raw/main/Apps/Location%20-%20notAperson%20(Droptop%20App).rmskin",
                "secondary_link": "",
                "image_url": "https://raw.githubusercontent.com/Droptop-Four/GlobalData/main/data/community_apps/img/Location-notAperson.webp",
                "authorised_members": [584542239900827665, 330345930198876161, 736395826670207088]
            }
        },
        {
            "app": {
                "id": 2,
                "uuid": "b7a7627e-96c7-4c42-a6ac-6d199f7ba378",
                "name": "Daily Quotes",
                "author": "Bunz",
                "author_id": 330345930198876161,
                "author_link": "https://github.com/66Bunz",
                "desc": "Shows a series of quotes, updating daily. Cycles through a new quote every 20 seconds, or use the scroll wheel to cycle through them manually.",
                "version": "1.0.7",
                "official_link": "https://github.com/66Bunz/DroptopFour-DailyQuotes",
                "direct_download_link": "https://github.com/Droptop-Four/Droptop-Community-Apps/raw/main/Apps/Daily%20Quotes%20-%20Bunz%20(Droptop%20App).rmskin",
                "secondary_link": "",
                "image_url": "https://raw.githubusercontent.com/Droptop-Four/GlobalData/main/data/community_apps/img/Daily_Quotes-Bunz.webp",
                "authorised_members": [584542239900827665, 330345930198876161, 330345930198876161]
            }
        },
        {
            "app": {
                "id": 1,
                "uuid": "ed3f7b7a-04fa-4531-9d75-0ea2d43e408c",
                "name": "Sample App",
                "author": "Cariboudjan",
                "author_id": 584542239900827665,
                "author_link": "https://github.com/Cariboudjan",
                "desc": "Default Sample App that shows what you can achieve by creating your own custom app.",
                "version": "2.0",
                "official_link": "",
                "direct_download_link": "https://github.com/Droptop-Four/Droptop-Community-Apps/raw/main/Apps/Sample%20App%20-%20Cariboudjan%20(Droptop%20App).rmskin",
                "secondary_link": "",
                "image_url": "https://raw.githubusercontent.com/Droptop-Four/GlobalData/main/data/community_apps/img/Sample_App-Cariboudjan.webp",
                "authorised_members": [584542239900827665, 330345930198876161, 584542239900827665]
            }
        }
    ]
}
